Workbook

Sheet LeiaMe
B2: MARINERS SUPPLY — OPERAÇÃO FASE 0 (MVP WHATSAPP)
B4: Como usar
B5: 1. Config: ajuste câmbio e percentuais (células amarelas).
B6: 2. Navios: lance o line-up da semana (ETA vem da agência parceira).
B7: 3. Pedidos: 1 linha por pedido; depósito e saldo calculam sozinhos.
B8: 4. Capitães: cadastre o código de cada boné; indicações somam sozinhas.
B9: 5. Caixa: lance entradas e saídas; saldo acumula sozinho.
B11: Legenda
B12: Azul = você digita (input) | C12: Preto = fórmula, não mexer
B13: Amarelo = premissa-chave (Config) | C13: Linha 2 de cada aba = exemplo real
B15: Resumo automático
B16: Pedidos registrados | C16: =COUNTA(Pedidos!A:A)-1
B17: GMV total (USD) | C17: =SUM(Pedidos!G:G)
B18: Depósitos recebidos (USD) | C18: =SUMIFS(Pedidos!H:H,Pedidos!K:K,"S")
B19: Saldo a receber na prancha (USD) | C19: =SUMIFS(Pedidos!I:I,Pedidos!L:L,"N")
B20: Crédito de capitães em aberto (USD) | C20: =SUM(Capitaes!H:H)

Sheet Config
A1: Premissa | B1: Valor | C1: Observação
A2: Câmbio USD → BRL (referência) | B2: 5.3 | C2: Atualizar 1x/semana; só para conversão informativa
A3: % depósito antecipado | B3: 0.3 | C3: Cobrado no link de pagamento ao confirmar o pedido
A4: % crédito do Capitão | B4: 0.05 | C4: Sobre o total dos pedidos indicados; pago em crédito, nunca dinheiro
A5: Janela de fechamento (horas antes do ETA) | B5: 26 | C5: Pedido fecha 26h antes da atracação

Sheet Catalogo
A1: Cód | B1: Item | C1: Categoria | D1: Fornecedor | E1: Custo (USD) | F1: Preço (USD) | G1: Margem % | H1: Preço ≈R$
A2: SIM20 | B2: eSIM Brasil 20 GB / 30d | C2: Conectividade | D2: eSIM white-label | E2: 8.5 | F2: 18 | G2: =(F2-E2)/F2 | H2: =F2*Config!$B$2
A3: SIM50 | B3: eSIM Brasil 50 GB / 30d | C3: Conectividade | D3: eSIM white-label | E3: 15 | F3: 32 | G3: =(F3-E3)/F3 | H3: =F3*Config!$B$2
A4: SNK1 | B4: Snack kit grande | C4: Comida | D4: Atacado (Assaí) | E4: 13 | F4: 25 | G4: =(F4-E4)/F4 | H4: =F4*Config!$B$2
A5: CAF1 | B5: Kit café brasileiro 500g | C5: Comida | D5: Atacado (Assaí) | E5: 9 | F5: 18 | G5: =(F5-E5)/F5 | H5: =F5*Config!$B$2
A6: BEB1 | B6: Drinks pack 12 latas (s/ álcool) | C6: Comida | D6: Atacado (Assaí) | E6: 8 | F6: 16 | G6: =(F6-E6)/F6 | H6: =F6*Config!$B$2
A7: HIG1 | B7: Kit higiene completo | C7: Cuidado | D7: Farmácia parceira | E7: 11 | F7: 22 | G7: =(F7-E7)/F7 | H7: =F7*Config!$B$2
A8: FAR1 | B8: Farmácia básica de bordo | C8: Cuidado | D8: Farmácia parceira | E8: 9.5 | F8: 19 | G8: =(F8-E8)/F8 | H8: =F8*Config!$B$2
A9: SOL1 | B9: Deck kit (protetor FPS50 + boné) | C9: Cuidado | D9: Farmácia parceira | E9: 10.5 | F9: 21 | G9: =(F9-E9)/F9 | H9: =F9*Config!$B$2
A10: JBL1 | B10: JBL Go 4 (lacrada + NF) | C10: Eletrônico | D10: Distribuidor oficial | E10: 32 | F10: 45 | G10: =(F10-E10)/F10 | H10: =F10*Config!$B$2
A11: POW1 | B11: Powerbank 20.000 mAh | C11: Eletrônico | D11: Distribuidor oficial | E11: 18 | F11: 29 | G11: =(F11-E11)/F11 | H11: =F11*Config!$B$2
A12: CAB1 | B12: Kit cabos + adaptador BR | C12: Eletrônico | D12: Distribuidor oficial | E12: 7 | F12: 15 | G12: =(F12-E12)/F12 | H12: =F12*Config!$B$2
A13: POK1 | B13: Poker set compacto | C13: Eletrônico | D13: Distribuidor oficial | E13: 7.5 | F13: 14 | G13: =(F13-E13)/F13 | H13: =F13*Config!$B$2

Sheet Navios
A1: Navio | B1: Linha/Armadora | C1: Agência | D1: ETA (data e hora) | E1: Berço | F1: Pedidos fecham em | G1: Status
A2: MSC LORENA | B2: MSC — Ásia/ECSA | C2: Wilson Sons | D2: 46258.597 | E2: 39 | F2: =IF(D2="","",D2-Config!$B$5/24) | G2: Aguardando
A3: CMA CGM MELODY | B3: CMA — Med/ECSA | C3: Unimar | D3: 46259.333 | E3: 33 | F3: =IF(D3="","",D3-Config!$B$5/24) | G3: Aguardando

Sheet Pedidos
A1: Nº | B1: Data | C1: Navio | D1: Cód. Capitão | E1: Cliente (nome/rank) | F1: Itens (códigos e qtd) | G1: Total (USD) | H1: Depósito (USD) | I1: Saldo prancha (USD) | J1: Status | K1: Dep. pago? | L1: Saldo pago? | M1: Foto entrega?
A2: MS-0001 | B2: 2026-08-22 | C2: MSC LORENA | D2: MS-ANDRES-39 | E2: Andres (Bosun) | F2: SIM20 x1, SNK1 x1, JBL1 x1 | G2: 88 | H2: =G2*Config!$B$3 | I2: =G2-H2 | J2: Comprando | K2: S | L2: N | M2: N
A3: MS-0002 | B3: 2026-08-22 | C3: MSC LORENA | D3: MS-ANDRES-39 | E3: Pedido coletivo (6 trip.) | F3: SNK1 x4, CAF1 x2, HIG1 x2 | G3: 180 | H3: =G3*Config!$B$3 | I3: =G3-H3 | J3: Novo | K3: S | L3: N | M3: N
A4: MS-0003 | B4: 2026-08-23 | C4: CMA CGM MELODY | E4: Cook | F4: SIM50 x2, BEB1 x3 | G4: 112 | H4: =G4*Config!$B$3 | I4: =G4-H4 | J4: Novo | K4: N | L4: N | M4: N

Sheet Capitaes
A1: Código | B1: Nome | C1: Navio / Linha | D1: Pedidos indicados | E1: GMV indicado (USD) | F1: Crédito ganho (USD) | G1: Crédito usado (USD) | H1: Saldo crédito (USD)
A2: MS-ANDRES-39 | B2: Andres Reyes | C2: MSC LORENA / Ásia-ECSA | D2: =COUNTIF(Pedidos!D:D,A2) | E2: =SUMIF(Pedidos!D:D,A2,Pedidos!G:G) | F2: =E2*Config!$B$4 | G2: 0 | H2: =F2-G2

Sheet Caixa
A1: Data | B1: Tipo | C1: Descrição | D1: Valor (USD) | E1: Valor (≈R$) | F1: Saldo acumulado (USD)
A2: 2026-08-22 | B2: Depósito recebido | C2: MS-0001 — 30% via link | D2: 26.4 | E2: =D2*Config!$B$2 | F2: =SUM($D$2:D2)
A3: 2026-08-23 | B3: Compra mercadoria | C3: Assaí — snacks e café (NF 1234) | D3: -34 | E3: =D3*Config!$B$2 | F3: =SUM($D$2:D3)
